setup.py
funport/__init__.py
funport.egg-info/PKG-INFO
funport.egg-info/SOURCES.txt
funport.egg-info/dependency_links.txt
funport.egg-info/not-zip-safe
funport.egg-info/top_level.txt