Metadata-Version: 1.0
Name: funport
Version: 0.1
Summary: the joke for funport
Home-page: UNKNOWN
Author: flying man
Author-email: 123@gmail.com
License: MIT
Platform: UNKNOWN
